{
  "Pera" : {
    "ime" : "Pera ALOO",
    "prezime" : null,
    "eMail" : null,
    "pol" : null,
    "datumRodjenja" : null,
    "status" : false,
    "nalog" : null,
    "zakazaneRecenzije" : [ ],
    "recenzijeZaIzmene" : [ ],
    "iteratorZakazaneRecenzije" : [ ],
    "iteratorRecenzijeZaIzmene" : [ ]
  },
  "Alo" : {
    "ime" : null,
    "prezime" : null,
    "eMail" : null,
    "pol" : null,
    "datumRodjenja" : null,
    "status" : false,
    "nalog" : null,
    "muzickoDjelo" : [ ],
    "preferiraniZanrovi" : [ ],
    "pratilac" : null,
    "pratite" : [ ],
    "onajKogaPrati" : [ ],
    "iteratorOnajKogaPrati" : [ ],
    "iteratorPratite" : [ ],
    "iteratorPreferiraniZanrovi" : [ ],
    "iteratorMuzickoDjelo" : [ ]
  },
  "Skera" : {
    "ime" : null,
    "prezime" : null,
    "eMail" : null,
    "pol" : null,
    "datumRodjenja" : null,
    "status" : false,
    "nalog" : null,
    "muzickoDjelo" : [ ],
    "preferiraniZanrovi" : [ ],
    "pratilac" : null,
    "istorijaRecenzija" : [ ],
    "zakazaneRecenzije" : [ ],
    "recezijaZaIzmenu" : [ ],
    "iteratorZakazaneRecenzije" : [ ],
    "iteratorRecezijaZaIzmenu" : [ ],
    "iteratorIstorijaRecenzija" : [ ],
    "iteratorPreferiraniZanrovi" : [ ],
    "iteratorMuzickoDjelo" : [ ]
  }
}